bambot/__init__.py
bambot/app.py
bambot/build.py
bambot/cli.py
bambot/docker_utils.py
bambot/project.py
bambot/run.py
bambot/utils.py
bambot/templates/Dockerfile
bambot/templates/agent_runner.py
bambot/templates/agent_template.py
bambot/templates/langchain_template.py
bambot/templates/requirements.txt
bambot/templates/server.py
bambot-0.4.5.dist-info/METADATA
bambot-0.4.5.dist-info/WHEEL
bambot-0.4.5.dist-info/entry_points.txt
bambot-0.4.5.dist-info/top_level.txt
bambot-0.4.5.dist-info/RECORD
