Metadata-Version: 2.1
Name: bambot
Version: 0.4.5
Summary: Containers for AI agents
Home-page: https://github.com/Bam-Corp/bambot
Author: Bam Corp
Author-email: spencer@bam.bot
Classifier: Development Status :: 4 - Beta
Classifier: Intended Audience :: Developers
Classifier: License :: OSI Approved :: MIT License
Classifier: Programming Language :: Python :: 3
Classifier: Programming Language :: Python :: 3.6
Classifier: Programming Language :: Python :: 3.7
Classifier: Programming Language :: Python :: 3.8
Classifier: Programming Language :: Python :: 3.9
Classifier: Programming Language :: Python :: 3.10
Classifier: Programming Language :: Python :: 3.11
Classifier: Programming Language :: Python :: 3.12
Requires-Python: >=3.6
Requires-Dist: click
Requires-Dist: docker
Requires-Dist: tqdm
Requires-Dist: python-dotenv
Requires-Dist: halo
Requires-Dist: colorama
